licofage/__init__.py
licofage/__main__.py
licofage/_version.py
licofage/addcut.cp310-win_amd64.pyd
licofage/api.py
licofage/argmisc.py
licofage/arraysorter.cp310-win_amd64.pyd
licofage/bareiss.py
licofage/cli.py
licofage/dfamin.cp310-win_amd64.pyd
licofage/dfau.py
licofage/flatadd.py
licofage/intmap.py
licofage/kit.py
licofage/lrseq.py
licofage/matrix.py
licofage/mincheck.py
licofage/misc.py
licofage/nfa.py
licofage/polybound.py
licofage/polytools.py
licofage/subst.py
licofage/ubound.py
licofage-0.9.2.dist-info/licenses/LICENSE
licofage-0.9.2.dist-info/METADATA
licofage-0.9.2.dist-info/WHEEL
licofage-0.9.2.dist-info/entry_points.txt
licofage-0.9.2.dist-info/top_level.txt
licofage-0.9.2.dist-info/RECORD
