Metadata-Version: 2.4
Name: licofage
Version: 0.9.2
Summary: Generate deterministic finite automata associated to linear equations expressed in the numeration system associated to a given substitution.
Maintainer-email: Nicolas Ollinger <nopid@free.fr>
Project-URL: Repository, https://github.com/nopid/licofage.git
Project-URL: Issues, https://github.com/nopid/licofage/issues
Classifier: Development Status :: 3 - Alpha
Classifier: Intended Audience :: Science/Research
Classifier: Topic :: Scientific/Engineering
Classifier: License :: OSI Approved :: CEA CNRS Inria Logiciel Libre License, version 2.1 (CeCILL-2.1)
Classifier: Operating System :: OS Independent
Classifier: Programming Language :: Python
Classifier: Programming Language :: Python :: 3
Classifier: Programming Language :: Python :: 3.9
Classifier: Programming Language :: Python :: 3.10
Classifier: Programming Language :: Python :: 3.11
Classifier: Programming Language :: Python :: 3.12
Requires-Python: >=3.9
License-File: LICENSE
Requires-Dist: numpy<2
Dynamic: license-file
